reindeer/__init__.py
reindeer/converdeer.py
reindeer/deer_flow.py
reindeer/enricher.py
test/__init__.py
test/test_converdeer.py
reindeer-0.1.5.dist-info/LICENSE.txt
reindeer-0.1.5.dist-info/METADATA
reindeer-0.1.5.dist-info/WHEEL
reindeer-0.1.5.dist-info/top_level.txt
reindeer-0.1.5.dist-info/RECORD
