Metadata-Version: 2.1
Name: reindeer
Version: 0.1.5
Summary: Reindeer ist eine Python Bibliothek um durch Verwendung des DEER-Frameworks, CSV-Datensätzen mit zusätzlichen Informationen aus LinkedData anzureichern.
Home-page: https://github.com/pypa/sampleproject
Author: Nils Kleber
Author-email: n.kleber@usu.de
License: UNKNOWN
Platform: UNKNOWN
Classifier: Programming Language :: Python :: 3
Classifier: License :: OSI Approved :: MIT License
Classifier: Operating System :: OS Independent
